{
  "_class": "shapePath",
  "booleanOperation": -1,
  "clippingMaskMode": 0,
  "do_objectID": "7A9BDA32-F426-4F92-B780-7DFDF4E97EFC",
  "edited": true,
  "exportOptions": {
    "_class": "exportOptions",
    "do_objectID": "D06B3C90-A5B5-47E8-84C1-5404AD31B668",
    "exportFormats": [
    ],
    "includedLayerIds": [
    ],
    "layerOptions": 0,
    "shouldTrim": false
  },
  "frame": {
    "_class": "rect",
    "constrainProportions": false,
    "do_objectID": "197147A9-C4A3-4406-8D65-8093BE13A1A3",
    "height": 4.000500000000001,
    "width": 4.000500000000001,
    "x": 6.999749999999999,
    "y": 6.999749999999999
  },
  "hasClippingMask": false,
  "isClosed": true,
  "isFixedToViewport": false,
  "isFlippedHorizontal": false,
  "isFlippedVertical": false,
  "isLocked": false,
  "isVisible": true,
  "layerListExpandedType": 0,
  "name": "Path",
  "nameIsFixed": false,
  "pointRadiusBehaviour": 1,
  "points": [
    {
      "_class": "curvePoint",
      "cornerRadius": 0,
      "curveFrom": "{1, 0.77615298087739049}",
      "curveMode": 2,
      "curveTo": "{1, 0.22384701912260951}",
      "hasCurveFrom": true,
      "hasCurveTo": true,
      "point": "{1, 0.5}"
    },
    {
      "_class": "curvePoint",
      "cornerRadius": 0,
      "curveFrom": "{0.22384701912260951, 1}",
      "curveMode": 2,
      "curveTo": "{0.77615298087739049, 1}",
      "hasCurveFrom": true,
      "hasCurveTo": true,
      "point": "{0.5, 1}"
    },
    {
      "_class": "curvePoint",
      "cornerRadius": 0,
      "curveFrom": "{0, 0.22384701912260951}",
      "curveMode": 2,
      "curveTo": "{0, 0.77615298087739049}",
      "hasCurveFrom": true,
      "hasCurveTo": true,
      "point": "{0, 0.5}"
    },
    {
      "_class": "curvePoint",
      "cornerRadius": 0,
      "curveFrom": "{0.77615298087739049, 0}",
      "curveMode": 2,
      "curveTo": "{0.22384701912260951, 0}",
      "hasCurveFrom": true,
      "hasCurveTo": true,
      "point": "{0.5, 0}"
    }
  ],
  "resizingConstraint": 63,
  "resizingType": 0,
  "rotation": 0,
  "shouldBreakMaskChain": false,
  "style": {
    "_class": "style",
    "do_objectID": "B054879D-6FEE-4DB5-B346-0D6BAD8A5B27",
    "endMarkerType": 0,
    "miterLimit": 10,
    "startMarkerType": 0,
    "windingRule": 1
  }
}