{
  "_class": "shapePath",
  "booleanOperation": -1,
  "clippingMaskMode": 0,
  "do_objectID": "D7E7EC26-F51F-478F-89E6-EE05DF1340BD",
  "edited": true,
  "exportOptions": {
    "_class": "exportOptions",
    "do_objectID": "97CA7D18-012C-451A-B867-A74BF465AB57",
    "exportFormats": [
    ],
    "includedLayerIds": [
    ],
    "layerOptions": 0,
    "shouldTrim": false
  },
  "frame": {
    "_class": "rect",
    "constrainProportions": false,
    "do_objectID": "E082C9A7-1F16-4E97-9331-2F38AD12E003",
    "height": 9.837750000000003,
    "width": 9.837749999999993,
    "x": 4.080750000000001,
    "y": 4.0815
  },
  "hasClippingMask": false,
  "isClosed": true,
  "isFixedToViewport": false,
  "isFlippedHorizontal": false,
  "isFlippedVertical": false,
  "isLocked": false,
  "isVisible": true,
  "layerListExpandedType": 0,
  "name": "Path",
  "nameIsFixed": false,
  "pointRadiusBehaviour": 1,
  "points": [
    {
      "_class": "curvePoint",
      "cornerRadius": 0,
      "curveFrom": "{0.68224441564382099, 0.00060989555538614067}",
      "curveMode": 3,
      "curveTo": "{0.91179385530227952, 0.011054356941373892}",
      "hasCurveFrom": true,
      "hasCurveTo": true,
      "point": "{0.74651215979263552, 0.0035068994434703255}"
    },
    {
      "_class": "curvePoint",
      "cornerRadius": 0,
      "curveFrom": "{0.33719600518411214, 0}",
      "curveMode": 2,
      "curveTo": "{0.66288023176031108, 0}",
      "hasCurveFrom": true,
      "hasCurveTo": true,
      "point": "{0.50003811847221158, 0}"
    },
    {
      "_class": "curvePoint",
      "cornerRadius": 0,
      "curveFrom": "{0.08820614469772052, 0.011054356941373824}",
      "curveMode": 3,
      "curveTo": "{0.31790805824502555, 0.00060989555538614067}",
      "hasCurveFrom": true,
      "hasCurveTo": true,
      "point": "{0.25364031409621102, 0.0035068994434703255}"
    },
    {
      "_class": "curvePoint",
      "cornerRadius": 0,
      "curveFrom": "{0.00068613249980943364, 0.31783182130060217}",
      "curveMode": 3,
      "curveTo": "{0.011130593885797051, 0.089425935808492799}",
      "hasCurveFrom": true,
      "hasCurveTo": true,
      "point": "{0.0036593733323168442, 0.25348784020736442}"
    },
    {
      "_class": "curvePoint",
      "cornerRadius": 0,
      "curveFrom": "{0, 0.66280399481588781}",
      "curveMode": 2,
      "curveTo": "{0, 0.33711976823968887}",
      "hasCurveFrom": true,
      "hasCurveTo": true,
      "point": "{0, 0.49996188152778831}"
    },
    {
      "_class": "curvePoint",
      "cornerRadius": 0,
      "curveFrom": "{0.011130593885797051, 0.91019287946939076}",
      "curveMode": 3,
      "curveTo": "{0.00068613249980943364, 0.68209194175497434}",
      "hasCurveFrom": true,
      "hasCurveTo": true,
      "point": "{0.0035831363878935513, 0.74643592284821225}"
    },
    {
      "_class": "curvePoint",
      "cornerRadius": 0,
      "curveFrom": "{0.31783182130060217, 0.99931386750019058}",
      "curveMode": 3,
      "curveTo": "{0.087901196920027416, 0.98886940611420293}",
      "hasCurveFrom": true,
      "hasCurveTo": true,
      "point": "{0.25356407715178769, 0.99641686361210635}"
    },
    {
      "_class": "curvePoint",
      "cornerRadius": 0,
      "curveFrom": "{0.66295646870473435, 1}",
      "curveMode": 2,
      "curveTo": "{0.33719600518411214, 1}",
      "hasCurveFrom": true,
      "hasCurveTo": true,
      "point": "{0.50003811847221158, 1}"
    },
    {
      "_class": "curvePoint",
      "cornerRadius": 0,
      "curveFrom": "{0.91194632919112595, 0.9889456430586262}",
      "curveMode": 3,
      "curveTo": "{0.68224441564382099, 0.99939010444461396}",
      "hasCurveFrom": true,
      "hasCurveTo": true,
      "point": "{0.74651215979263552, 0.99649310055652973}"
    },
    {
      "_class": "curvePoint",
      "cornerRadius": 0,
      "curveFrom": "{0.99939010444461396, 0.68216817869939783}",
      "curveMode": 3,
      "curveTo": "{0.9889456430586262, 0.91042159030266057}",
      "hasCurveFrom": true,
      "hasCurveTo": true,
      "point": "{0.99649310055652973, 0.74651215979263563}"
    },
    {
      "_class": "curvePoint",
      "cornerRadius": 0,
      "curveFrom": "{1, 0.33719600518411219}",
      "curveMode": 2,
      "curveTo": "{1, 0.66288023176031119}",
      "hasCurveFrom": true,
      "hasCurveTo": true,
      "point": "{1, 0.50003811847221169}"
    },
    {
      "_class": "curvePoint",
      "cornerRadius": 0,
      "curveFrom": "{0.9889456430586262, 0.089502172752916151}",
      "curveMode": 3,
      "curveTo": "{0.99939010444461396, 0.31790805824502566}",
      "hasCurveFrom": true,
      "hasCurveTo": true,
      "point": "{0.99649310055652973, 0.25364031409621113}"
    }
  ],
  "resizingConstraint": 63,
  "resizingType": 0,
  "rotation": 0,
  "shouldBreakMaskChain": false,
  "style": {
    "_class": "style",
    "do_objectID": "399BC8DC-4FF3-4EFD-B2FC-511F9F50A78A",
    "endMarkerType": 0,
    "miterLimit": 10,
    "startMarkerType": 0,
    "windingRule": 1
  }
}